baymax/__init__.py
baymax/api.py
baymax/args.py
baymax/bot.py
baymax/logger.py
baymax/markups.py
baymax/storage.py
baymax-0.0.5.dist-info/LICENSE
baymax-0.0.5.dist-info/METADATA
baymax-0.0.5.dist-info/WHEEL
baymax-0.0.5.dist-info/top_level.txt
baymax-0.0.5.dist-info/RECORD
