Metadata-Version: 2.1
Name: baymax
Version: 0.0.5
Summary: A simple telegram bot framework on top of Python asyncio
Home-page: https://github.com/dmrz/baymax
Author: Dima Moroz
Author-email: me@dimamoroz.com
License: MIT
Keywords: telegram bot asyncio
Platform: UNKNOWN
Classifier: Development Status :: 3 - Alpha
Classifier: Intended Audience :: Developers
Classifier: Topic :: Software Development :: Libraries :: Application Frameworks
Classifier: License :: OSI Approved :: MIT License
Classifier: Programming Language :: Python :: 3.7
Requires-Python: >=3.7
Requires-Dist: aiodns (==2.0.0)
Requires-Dist: aiohttp (==3.5.4)
Requires-Dist: async-timeout (==3.0.1)
Requires-Dist: colorlog (==4.0.2)
Requires-Dist: uvloop (==0.12.2)
